frappyflaskimpex/__init__.py
frappyflaskimpex/impex_api.py
frappyflaskimpex-1.0.0.dist-info/LICENSE
frappyflaskimpex-1.0.0.dist-info/METADATA
frappyflaskimpex-1.0.0.dist-info/WHEEL
frappyflaskimpex-1.0.0.dist-info/top_level.txt
frappyflaskimpex-1.0.0.dist-info/RECORD
