Metadata-Version: 2.1
Name: frappyflaskimpex
Version: 1.0.0
Summary: Flask Endpoints for Database Import and Export
Home-page: https://github.com/ilfrich/frappy-flask-impex
Author: Peter Ilfrich
Author-email: das-peter@gmx.de
License: UNKNOWN
Platform: UNKNOWN
Requires-Dist: flask
Requires-Dist: pbu
